symenergy/__init__.py
symenergy/assets/__init__.py
symenergy/assets/curtailment.py
symenergy/assets/plant.py
symenergy/assets/storage.py
symenergy/auxiliary/__init__.py
symenergy/auxiliary/constrcomb.py
symenergy/auxiliary/decorators.py
symenergy/auxiliary/io.py
symenergy/auxiliary/parallelization.py
symenergy/auxiliary/params.py
symenergy/cache/__init__.py
symenergy/cache/l4B7A1DA2C1E2_eval_temp.py
symenergy/core/__init__.py
symenergy/core/altlinsolve.py
symenergy/core/asset.py
symenergy/core/collections.py
symenergy/core/component.py
symenergy/core/constraint.py
symenergy/core/model.py
symenergy/core/parameter.py
symenergy/core/slot.py
symenergy/core/variable.py
symenergy/evaluator/__init__.py
symenergy/evaluator/evaluator.py
symenergy/evaluator/plotting.py
symenergy/patches/__init__.py
symenergy/patches/symenergy_solveset.py
symenergy/patches/sympy_linear_coeffs.py
symenergy/patches/sympy_linsolve.py
SymEnergy-1.0.7.dist-info/AUTHORS
SymEnergy-1.0.7.dist-info/LICENSE
SymEnergy-1.0.7.dist-info/METADATA
SymEnergy-1.0.7.dist-info/WHEEL
SymEnergy-1.0.7.dist-info/top_level.txt
SymEnergy-1.0.7.dist-info/RECORD
